battery_notifier/__init__.py
battery_notifier/battery_notifier.py
battery_notifier/config.py
battery_notifier-0.3.dist-info/LICENSE
battery_notifier-0.3.dist-info/METADATA
battery_notifier-0.3.dist-info/WHEEL
battery_notifier-0.3.dist-info/entry_points.txt
battery_notifier-0.3.dist-info/top_level.txt
battery_notifier-0.3.dist-info/RECORD
