Metadata-Version: 2.1
Name: battery_notifier
Version: 0.3
Summary: Sends desktop notifications for low and critical battery warnings, and optionally when charging/discharging state changes
Author-email: Brenton Leighton <12228142+brenton-leighton@users.noreply.github.com>
Maintainer-email: Brenton Leighton <12228142+brenton-leighton@users.noreply.github.com>
License: MIT License
Project-URL: Homepage, https://github.com/brenton-leighton/battery_notifier
Keywords: linux,battery,dbus,upower
Requires-Python: >=3.9
License-File: LICENSE
Requires-Dist: pydbus
Requires-Dist: PyGObject
